[
  {
    "line": 1,
    "elements": [
      {
        "line": 21,
        "name": "Add new users to the table list",
        "description": "",
        "id": "add-new-users-to-the-table;add-new-users-to-the-table-list;;2",
        "after": [
          {
            "result": {
              "duration": 700907100,
              "status": "passed"
            },
            "match": {
              "location": "AddUserSteps.tearDown()"
            }
          }
        ],
        "type": "scenario",
        "keyword": "Scenario Outline",
        "steps": [
          {
            "result": {
              "duration": 15474589800,
              "status": "passed"
            },
            "line": 4,
            "name": "a user has launched the website",
            "match": {
              "location": "AddUserSteps.a_user_has_launched_the_browser()"
            },
            "keyword": "Given "
          },
          {
            "result": {
              "status": "undefined"
            },
            "line": 5,
            "name": "a user checks if a username already exists on the list\"sipha1\"",
            "match": {},
            "matchedColumns": [
              2
            ],
            "keyword": "When "
          },
          {
            "result": {
              "status": "skipped"
            },
            "line": 6,
            "name": "a user clicks on the add user button",
            "match": {
              "location": "AddUserSteps.a_user_clicks_on_the_add_user_button()"
            },
            "keyword": "When "
          },
          {
            "result": {
              "status": "skipped"
            },
            "line": 7,
            "name": "a user enters firstname on the populated modal screen\"sipha1\"",
            "match": {
              "arguments": [
                {
                  "val": "sipha1",
                  "offset": 54
                }
              ],
              "location": "AddUserSteps.a_user_populate_firstname(String)"
            },
            "matchedColumns": [
              0
            ],
            "keyword": "And "
          },
          {
            "result": {
              "status": "skipped"
            },
            "line": 8,
            "name": "a user enters lastname \"Nipha1\"",
            "match": {
              "arguments": [
                {
                  "val": "Nipha1",
                  "offset": 24
                }
              ],
              "location": "AddUserSteps.a_user_populate_surname(String)"
            },
            "matchedColumns": [
              1
            ],
            "keyword": "And "
          },
          {
            "result": {
              "status": "skipped"
            },
            "line": 9,
            "name": "a user enters username \"sipha1\"",
            "match": {
              "arguments": [
                {
                  "val": "sipha1",
                  "offset": 24
                }
              ],
              "location": "AddUserSteps.a_user_populate_username(String)"
            },
            "matchedColumns": [
              2
            ],
            "keyword": "And "
          },
          {
            "result": {
              "status": "skipped"
            },
            "line": 10,
            "name": "a user enters password \"123\"",
            "match": {
              "arguments": [
                {
                  "val": "123",
                  "offset": 24
                }
              ],
              "location": "AddUserSteps.a_user_populate_password(String)"
            },
            "matchedColumns": [
              3
            ],
            "keyword": "And "
          },
          {
            "result": {
              "status": "skipped"
            },
            "line": 11,
            "name": "a user select a company \"Company AAA\"",
            "match": {
              "arguments": [
                {
                  "val": "Company AAA",
                  "offset": 25
                }
              ],
              "location": "AddUserSteps.a_user_select_a_company(String)"
            },
            "matchedColumns": [
              4
            ],
            "keyword": "And "
          },
          {
            "result": {
              "status": "skipped"
            },
            "line": 12,
            "name": "a user choose a role \"Admin\"",
            "match": {
              "arguments": [
                {
                  "val": "Admin",
                  "offset": 22
                }
              ],
              "location": "AddUserSteps.a_user_choose_a_role(String)"
            },
            "matchedColumns": [
              5
            ],
            "keyword": "And "
          },
          {
            "result": {
              "status": "skipped"
            },
            "line": 13,
            "name": "a user enters email \"sipha@mail.com\"",
            "match": {
              "arguments": [
                {
                  "val": "sipha@mail.com",
                  "offset": 21
                }
              ],
              "location": "AddUserSteps.a_user_populate_email(String)"
            },
            "matchedColumns": [
              6
            ],
            "keyword": "And "
          },
          {
            "result": {
              "status": "skipped"
            },
            "line": 14,
            "name": "a user enters cellphoneNo \"043\"",
            "match": {
              "arguments": [
                {
                  "val": "043",
                  "offset": 27
                }
              ],
              "location": "AddUserSteps.a_user_populate_cellphone(String)"
            },
            "matchedColumns": [
              7
            ],
            "keyword": "And "
          },
          {
            "result": {
              "status": "skipped"
            },
            "line": 15,
            "name": "a user saves a created user",
            "match": {
              "location": "AddUserSteps.a_user_saves_a_created_user()"
            },
            "keyword": "And "
          },
          {
            "result": {
              "status": "skipped"
            },
            "line": 16,
            "name": "a user checks if a user is added \"sipha1\"",
            "match": {
              "arguments": [
                {
                  "val": "sipha1",
                  "offset": 34
                }
              ],
              "location": "AddUserSteps.a_user_checks_if_a_user_is_added(String)"
            },
            "matchedColumns": [
              2
            ],
            "keyword": "And "
          }
        ]
      },
      {
        "line": 22,
        "name": "Add new users to the table list",
        "description": "",
        "id": "add-new-users-to-the-table;add-new-users-to-the-table-list;;3",
        "after": [
          {
            "result": {
              "duration": 676204000,
              "status": "passed"
            },
            "match": {
              "location": "AddUserSteps.tearDown()"
            }
          }
        ],
        "type": "scenario",
        "keyword": "Scenario Outline",
        "steps": [
          {
            "result": {
              "duration": 13726754400,
              "status": "passed"
            },
            "line": 4,
            "name": "a user has launched the website",
            "match": {
              "location": "AddUserSteps.a_user_has_launched_the_browser()"
            },
            "keyword": "Given "
          },
          {
            "result": {
              "status": "undefined"
            },
            "line": 5,
            "name": "a user checks if a username already exists on the list\"sipha2\"",
            "match": {},
            "matchedColumns": [
              2
            ],
            "keyword": "When "
          },
          {
            "result": {
              "status": "skipped"
            },
            "line": 6,
            "name": "a user clicks on the add user button",
            "match": {
              "location": "AddUserSteps.a_user_clicks_on_the_add_user_button()"
            },
            "keyword": "When "
          },
          {
            "result": {
              "status": "skipped"
            },
            "line": 7,
            "name": "a user enters firstname on the populated modal screen\"sipha2\"",
            "match": {
              "arguments": [
                {
                  "val": "sipha2",
                  "offset": 54
                }
              ],
              "location": "AddUserSteps.a_user_populate_firstname(String)"
            },
            "matchedColumns": [
              0
            ],
            "keyword": "And "
          },
          {
            "result": {
              "status": "skipped"
            },
            "line": 8,
            "name": "a user enters lastname \"Nipha2\"",
            "match": {
              "arguments": [
                {
                  "val": "Nipha2",
                  "offset": 24
                }
              ],
              "location": "AddUserSteps.a_user_populate_surname(String)"
            },
            "matchedColumns": [
              1
            ],
            "keyword": "And "
          },
          {
            "result": {
              "status": "skipped"
            },
            "line": 9,
            "name": "a user enters username \"sipha2\"",
            "match": {
              "arguments": [
                {
                  "val": "sipha2",
                  "offset": 24
                }
              ],
              "location": "AddUserSteps.a_user_populate_username(String)"
            },
            "matchedColumns": [
              2
            ],
            "keyword": "And "
          },
          {
            "result": {
              "status": "skipped"
            },
            "line": 10,
            "name": "a user enters password \"123\"",
            "match": {
              "arguments": [
                {
                  "val": "123",
                  "offset": 24
                }
              ],
              "location": "AddUserSteps.a_user_populate_password(String)"
            },
            "matchedColumns": [
              3
            ],
            "keyword": "And "
          },
          {
            "result": {
              "status": "skipped"
            },
            "line": 11,
            "name": "a user select a company \"Company BBB\"",
            "match": {
              "arguments": [
                {
                  "val": "Company BBB",
                  "offset": 25
                }
              ],
              "location": "AddUserSteps.a_user_select_a_company(String)"
            },
            "matchedColumns": [
              4
            ],
            "keyword": "And "
          },
          {
            "result": {
              "status": "skipped"
            },
            "line": 12,
            "name": "a user choose a role \"Customer\"",
            "match": {
              "arguments": [
                {
                  "val": "Customer",
                  "offset": 22
                }
              ],
              "location": "AddUserSteps.a_user_choose_a_role(String)"
            },
            "matchedColumns": [
              5
            ],
            "keyword": "And "
          },
          {
            "result": {
              "status": "skipped"
            },
            "line": 13,
            "name": "a user enters email \"siphe@mail.com\"",
            "match": {
              "arguments": [
                {
                  "val": "siphe@mail.com",
                  "offset": 21
                }
              ],
              "location": "AddUserSteps.a_user_populate_email(String)"
            },
            "matchedColumns": [
              6
            ],
            "keyword": "And "
          },
          {
            "result": {
              "status": "skipped"
            },
            "line": 14,
            "name": "a user enters cellphoneNo \"021\"",
            "match": {
              "arguments": [
                {
                  "val": "021",
                  "offset": 27
                }
              ],
              "location": "AddUserSteps.a_user_populate_cellphone(String)"
            },
            "matchedColumns": [
              7
            ],
            "keyword": "And "
          },
          {
            "result": {
              "status": "skipped"
            },
            "line": 15,
            "name": "a user saves a created user",
            "match": {
              "location": "AddUserSteps.a_user_saves_a_created_user()"
            },
            "keyword": "And "
          },
          {
            "result": {
              "status": "skipped"
            },
            "line": 16,
            "name": "a user checks if a user is added \"sipha2\"",
            "match": {
              "arguments": [
                {
                  "val": "sipha2",
                  "offset": 34
                }
              ],
              "location": "AddUserSteps.a_user_checks_if_a_user_is_added(String)"
            },
            "matchedColumns": [
              2
            ],
            "keyword": "And "
          }
        ]
      },
      {
        "line": 23,
        "name": "Add new users to the table list",
        "description": "",
        "id": "add-new-users-to-the-table;add-new-users-to-the-table-list;;4",
        "after": [
          {
            "result": {
              "duration": 664669000,
              "status": "passed"
            },
            "match": {
              "location": "AddUserSteps.tearDown()"
            }
          }
        ],
        "type": "scenario",
        "keyword": "Scenario Outline",
        "steps": [
          {
            "result": {
              "duration": 13552994800,
              "status": "passed"
            },
            "line": 4,
            "name": "a user has launched the website",
            "match": {
              "location": "AddUserSteps.a_user_has_launched_the_browser()"
            },
            "keyword": "Given "
          },
          {
            "result": {
              "status": "undefined"
            },
            "line": 5,
            "name": "a user checks if a username already exists on the list\"sipha2\"",
            "match": {},
            "matchedColumns": [
              2
            ],
            "keyword": "When "
          },
          {
            "result": {
              "status": "skipped"
            },
            "line": 6,
            "name": "a user clicks on the add user button",
            "match": {
              "location": "AddUserSteps.a_user_clicks_on_the_add_user_button()"
            },
            "keyword": "When "
          },
          {
            "result": {
              "status": "skipped"
            },
            "line": 7,
            "name": "a user enters firstname on the populated modal screen\"sipha3\"",
            "match": {
              "arguments": [
                {
                  "val": "sipha3",
                  "offset": 54
                }
              ],
              "location": "AddUserSteps.a_user_populate_firstname(String)"
            },
            "matchedColumns": [
              0
            ],
            "keyword": "And "
          },
          {
            "result": {
              "status": "skipped"
            },
            "line": 8,
            "name": "a user enters lastname \"Nipha3\"",
            "match": {
              "arguments": [
                {
                  "val": "Nipha3",
                  "offset": 24
                }
              ],
              "location": "AddUserSteps.a_user_populate_surname(String)"
            },
            "matchedColumns": [
              1
            ],
            "keyword": "And "
          },
          {
            "result": {
              "status": "skipped"
            },
            "line": 9,
            "name": "a user enters username \"sipha2\"",
            "match": {
              "arguments": [
                {
                  "val": "sipha2",
                  "offset": 24
                }
              ],
              "location": "AddUserSteps.a_user_populate_username(String)"
            },
            "matchedColumns": [
              2
            ],
            "keyword": "And "
          },
          {
            "result": {
              "status": "skipped"
            },
            "line": 10,
            "name": "a user enters password \"123\"",
            "match": {
              "arguments": [
                {
                  "val": "123",
                  "offset": 24
                }
              ],
              "location": "AddUserSteps.a_user_populate_password(String)"
            },
            "matchedColumns": [
              3
            ],
            "keyword": "And "
          },
          {
            "result": {
              "status": "skipped"
            },
            "line": 11,
            "name": "a user select a company \"Company BBB\"",
            "match": {
              "arguments": [
                {
                  "val": "Company BBB",
                  "offset": 25
                }
              ],
              "location": "AddUserSteps.a_user_select_a_company(String)"
            },
            "matchedColumns": [
              4
            ],
            "keyword": "And "
          },
          {
            "result": {
              "status": "skipped"
            },
            "line": 12,
            "name": "a user choose a role \"Customer\"",
            "match": {
              "arguments": [
                {
                  "val": "Customer",
                  "offset": 22
                }
              ],
              "location": "AddUserSteps.a_user_choose_a_role(String)"
            },
            "matchedColumns": [
              5
            ],
            "keyword": "And "
          },
          {
            "result": {
              "status": "skipped"
            },
            "line": 13,
            "name": "a user enters email \"siphe@mail.com\"",
            "match": {
              "arguments": [
                {
                  "val": "siphe@mail.com",
                  "offset": 21
                }
              ],
              "location": "AddUserSteps.a_user_populate_email(String)"
            },
            "matchedColumns": [
              6
            ],
            "keyword": "And "
          },
          {
            "result": {
              "status": "skipped"
            },
            "line": 14,
            "name": "a user enters cellphoneNo \"041\"",
            "match": {
              "arguments": [
                {
                  "val": "041",
                  "offset": 27
                }
              ],
              "location": "AddUserSteps.a_user_populate_cellphone(String)"
            },
            "matchedColumns": [
              7
            ],
            "keyword": "And "
          },
          {
            "result": {
              "status": "skipped"
            },
            "line": 15,
            "name": "a user saves a created user",
            "match": {
              "location": "AddUserSteps.a_user_saves_a_created_user()"
            },
            "keyword": "And "
          },
          {
            "result": {
              "status": "skipped"
            },
            "line": 16,
            "name": "a user checks if a user is added \"sipha2\"",
            "match": {
              "arguments": [
                {
                  "val": "sipha2",
                  "offset": 34
                }
              ],
              "location": "AddUserSteps.a_user_checks_if_a_user_is_added(String)"
            },
            "matchedColumns": [
              2
            ],
            "keyword": "And "
          }
        ]
      }
    ],
    "name": "Add new users to the table",
    "description": "",
    "id": "add-new-users-to-the-table",
    "keyword": "Feature",
    "uri": "AddUser.feature"
  }
]